{"cameraMode":{"drawMode":0,"name":"Shaded","section":"Shading Mode"},"sceneLighting":true,"audioPlay":false,"sceneViewState":{"showFog":true,"showMaterialUpdate":false,"showSkybox":true,"showFlares":true,"showImageEffects":true,"showParticleSystems":true},"in2DMode":false,"pivot":{"x":149.43777465820313,"y":323.06036376953127,"z":75.1534423828125},"rotation":{"x":-0.07673157006502152,"y":0.00807335413992405,"z":-0.0006213200394995511,"w":-0.9970192909240723},"size":1125.2034912109375,"orthographic":false}